pimm/__init__.py
pimm/__main__.py
pimm/color_print.py
pimm/mirrors.json
pimm/mirrors_base.json
pimm/pimm_const.py
pimm/pimm_module.py
pimm-0.0.6.dist-info/LICENSE
pimm-0.0.6.dist-info/METADATA
pimm-0.0.6.dist-info/WHEEL
pimm-0.0.6.dist-info/entry_points.txt
pimm-0.0.6.dist-info/top_level.txt
pimm-0.0.6.dist-info/RECORD
